pyomc.py
pyomc-1.0.0.dist-info/LICENSE
pyomc-1.0.0.dist-info/METADATA
pyomc-1.0.0.dist-info/WHEEL
pyomc-1.0.0.dist-info/entry_points.txt
pyomc-1.0.0.dist-info/top_level.txt
pyomc-1.0.0.dist-info/RECORD
