Metadata-Version: 2.1
Name: pyomc
Version: 1.0.0
Summary: UNKNOWN
Home-page: https://github.com/StephenFerrari14/pyomc
Author: Stephen Ferrari
Author-email: stephenferrari14@gmail.com
License: UNKNOWN
Platform: UNKNOWN
Requires-Python: >=3.6
Requires-Dist: Click
Requires-Dist: xmltodict
